st_customer_journey/__init__.py
st_customer_journey/frontend/build/asset-manifest.json
st_customer_journey/frontend/build/bootstrap.min.css
st_customer_journey/frontend/build/index.html
st_customer_journey/frontend/build/precache-manifest.13eeba20dfa82ab82561b520c3e67447.js
st_customer_journey/frontend/build/precache-manifest.717e5da6a970b0bcca107104fec7916f.js
st_customer_journey/frontend/build/service-worker.js
st_customer_journey/frontend/build/static/js/2.e7935c3f.chunk.js
st_customer_journey/frontend/build/static/js/2.e7935c3f.chunk.js.LICENSE.txt
st_customer_journey/frontend/build/static/js/2.e7935c3f.chunk.js.map
st_customer_journey/frontend/build/static/js/main.3358f16a.chunk.js
st_customer_journey/frontend/build/static/js/main.3358f16a.chunk.js.map
st_customer_journey/frontend/build/static/js/main.f95d456c.chunk.js
st_customer_journey/frontend/build/static/js/main.f95d456c.chunk.js.map
st_customer_journey/frontend/build/static/js/runtime-main.92f044aa.js
st_customer_journey/frontend/build/static/js/runtime-main.92f044aa.js.map
st_customer_journey-0.0.2.dist-info/LICENSE
st_customer_journey-0.0.2.dist-info/METADATA
st_customer_journey-0.0.2.dist-info/WHEEL
st_customer_journey-0.0.2.dist-info/top_level.txt
st_customer_journey-0.0.2.dist-info/RECORD
