Metadata-Version: 2.1
Name: st-customer-journey
Version: 0.0.2
Summary: Streamlit Component to display a customer journey
Author: 
Author-email: 
Requires-Python: >=3.6
License-File: LICENSE
Requires-Dist: streamlit >=0.63
